PySP/Analysis.py
PySP/Plot.py
PySP/Signal.py
PySP/__init__.py
PySP/_plot_init.py
PySP/_Analysis_Module/ModeAnalysis.py
PySP/_Analysis_Module/SpectrumAnalysis.py
PySP/_Analysis_Module/core.py
PySP/_Assist_Module/Decorators.py
PySP/_Assist_Module/Dependencies.py
PySP/_Assist_Module/Docstring.py
PySP/_Assist_Module/times+simsun.ttf
PySP/_Plot_Module/LinePlot.py
PySP/_Plot_Module/PlotPlugin.py
PySP/_Plot_Module/core.py
PySP/_Signal_Module/SignalRead.py
PySP/_Signal_Module/SignalSampling.py
PySP/_Signal_Module/SimulateSignal.py
PySP/_Signal_Module/core.py
pysp_xcw-7.5.4.dist-info/METADATA
pysp_xcw-7.5.4.dist-info/WHEEL
pysp_xcw-7.5.4.dist-info/top_level.txt
pysp_xcw-7.5.4.dist-info/RECORD
