Metadata-Version: 2.4
Name: pysp-xcw
Version: 7.5.4
Summary: Various classic and modern signal analysis and processing algorithms are implemented.
Home-page: https://github.com/xcw1129/PySP
Author: Xiong Chengwen
Author-email: xcw1824@outlook.com
Project-URL: Bug Tracker, https://github.com/xcw1129/PySP/issues
Project-URL: Source Code, https://github.com/xcw1129/PySP
Keywords: signal processing,spectral analysis,time-frequency analysis,feature extraction,signal decomposition
Classifier: Programming Language :: Python :: 3
Classifier: Intended Audience :: Science/Research
Requires-Python: >=3.7
Requires-Dist: numpy>=1.21.0
Requires-Dist: scipy>=1.7.0
Requires-Dist: matplotlib>=3.4.0
Dynamic: author
Dynamic: author-email
Dynamic: classifier
Dynamic: description
Dynamic: description-content-type
Dynamic: home-page
Dynamic: keywords
Dynamic: project-url
Dynamic: requires-dist
Dynamic: requires-python
Dynamic: summary
